LICENSE
verseml/__init__.py
verseml-0.1.0.dist-info/entry_points.txt
verseml-0.1.0.dist-info/LICENSE
verseml-0.1.0.dist-info/WHEEL
verseml-0.1.0.dist-info/METADATA
verseml-0.1.0.dist-info/RECORD
