Metadata-Version: 2.1
Name: verseml
Version: 0.1.0
Summary: 
Home-page: https://github.com/verseml/verseml
License: MIT
Keywords: ML,training,deployment
Author: camjw
Author-email: camjw119@gmail.com
Requires-Python: >=3.8,<4.0
Classifier: License :: OSI Approved :: MIT License
Classifier: Programming Language :: Python :: 3
Classifier: Programming Language :: Python :: 3.8
Classifier: Programming Language :: Python :: 3.9
Project-URL: Repository, https://github.com/verseml/verseml
